[
    {
        "simulation": "DAY_AHEAD",
        "resolution": 300,
        "category": "Generator",
        "component_name": "solar",
        "module": "PowerSystems",
        "type": "SingleTimeSeries",
        "name": "max_active_power",
        "scaling_factor_multiplier": "get_max_active_power",
        "scaling_factor_multiplier_module": "PowerSystems",
        "normalization_factor": 1,
        "data_file": "pv.csv"
    },
    {
        "simulation": "DAY_AHEAD",
        "resolution": 300,
        "category": "ElectricLoad",
        "component_name": "load",
        "module": "PowerSystems",
        "type": "SingleTimeSeries",
        "name": "max_active_power",
        "scaling_factor_multiplier": "get_max_active_power",
        "scaling_factor_multiplier_module": "PowerSystems",
        "normalization_factor": 1,
        "data_file": "load.csv"
    },
    {
        "simulation": "DAY_AHEAD",
        "resolution": 300,
        "category": "Generator",
        "component_name": "wind",
        "module": "PowerSystems",
        "type": "SingleTimeSeries",
        "name": "max_active_power",
        "scaling_factor_multiplier": "get_max_active_power",
        "scaling_factor_multiplier_module": "PowerSystems",
        "normalization_factor": 1,
        "data_file": "wind.csv"
    }
]